README.rst
setup.cfg
setup.py
gleeful/__init__.py
gleeful/accessory.py
gleeful.egg-info/PKG-INFO
gleeful.egg-info/SOURCES.txt
gleeful.egg-info/dependency_links.txt
gleeful.egg-info/requires.txt
gleeful.egg-info/top_level.txt
gleeful/services/__init__.py
gleeful/services/base.py
gleeful/services/display_switch.py
gleeful/services/garage_door.py
gleeful/services/temperature.py