Metadata-Version: 1.1
Name: gleeful
Version: 0.1.3
Summary: HomeKit Accessory Protocol (HAP) wrapper for Python
Home-page: https://bitbucket.org/schinckel/gleeful/
Author: Matthew Schinckel
Author-email: matt@schinckel.net
License: UNKNOWN
Platform: UNKNOWN
Classifier: Development Status :: 3 - Alpha
Classifier: Intended Audience :: Developers
Classifier: License :: OSI Approved :: MIT License
Classifier: Operating System :: OS Independent
Classifier: Programming Language :: Python :: 3.6
Classifier: Programming Language :: Python
Classifier: Topic :: Home Automation
Classifier: Topic :: Software Development :: Libraries :: Python Modules
